danidisp.py
danidisp-0.1.5.dist-info/LICENSE
danidisp-0.1.5.dist-info/METADATA
danidisp-0.1.5.dist-info/WHEEL
danidisp-0.1.5.dist-info/top_level.txt
danidisp-0.1.5.dist-info/RECORD
