Metadata-Version: 2.1
Name: danidisp
Version: 0.1.5
Summary: My own package: every useful function I want to use
Home-page: https://github.com/DanieleDiSpirito/danidisp
Author: Daniele Di Spirito
Author-email: danieledisp@proton.me
License: UNKNOWN
Platform: UNKNOWN
License-File: LICENSE
